{
  "generated_at": "2026-05-22T17:34:01.670Z",
  "product_version": "1.0.37",
  "review_required": true,
  "legal_change_claimed": false,
  "public_note": "Backend-derived metadata only. Review required before any legal or client use. Not legal advice.",
  "map_version": "T080",
  "markers": [
    {
      "jurisdiction_id": "eu",
      "label": "European Union",
      "region": "Europe",
      "maturity_score": 85,
      "activity_score": 85,
      "freshness_score": 55,
      "confidence_score": 55,
      "maturity_level": "high",
      "activity_level": "high",
      "source_freshness": "medium",
      "coverage_confidence": "medium",
      "status_headline": "EU AI Act adopted — implementation phase",
      "latest_change_at": null,
      "source_count": 7,
      "regulation_count": 2,
      "review_required": true,
      "review_status": "review_required"
    },
    {
      "jurisdiction_id": "uk",
      "label": "United Kingdom",
      "region": "Europe",
      "maturity_score": 55,
      "activity_score": 55,
      "freshness_score": 55,
      "confidence_score": 55,
      "maturity_level": "medium",
      "activity_level": "medium",
      "source_freshness": "medium",
      "coverage_confidence": "medium",
      "status_headline": "Pro-innovation AI regulation approach + ICO guidance",
      "latest_change_at": null,
      "source_count": 3,
      "regulation_count": 2,
      "review_required": true,
      "review_status": "review_required"
    },
    {
      "jurisdiction_id": "us-federal",
      "label": "United States (federal)",
      "region": "Americas",
      "maturity_score": 55,
      "activity_score": 85,
      "freshness_score": 55,
      "confidence_score": 55,
      "maturity_level": "medium",
      "activity_level": "high",
      "source_freshness": "medium",
      "coverage_confidence": "medium",
      "status_headline": "Federal AI policy portal, OMB, FTC, NIST RMF",
      "latest_change_at": null,
      "source_count": 4,
      "regulation_count": 4,
      "review_required": true,
      "review_status": "review_required"
    },
    {
      "jurisdiction_id": "us-colorado",
      "label": "Colorado (United States)",
      "region": "Americas",
      "maturity_score": 55,
      "activity_score": 30,
      "freshness_score": 30,
      "confidence_score": 30,
      "maturity_level": "medium",
      "activity_level": "low",
      "source_freshness": "low",
      "coverage_confidence": "low",
      "status_headline": "Colorado AI Act (SB 24-205) — state level",
      "latest_change_at": null,
      "source_count": 1,
      "regulation_count": 1,
      "review_required": true,
      "review_status": "review_required"
    },
    {
      "jurisdiction_id": "canada",
      "label": "Canada",
      "region": "Americas",
      "maturity_score": 55,
      "activity_score": 55,
      "freshness_score": 55,
      "confidence_score": 30,
      "maturity_level": "medium",
      "activity_level": "medium",
      "source_freshness": "medium",
      "coverage_confidence": "low",
      "status_headline": "Federal responsible AI + OPC privacy guidance",
      "latest_change_at": null,
      "source_count": 1,
      "regulation_count": 1,
      "review_required": true,
      "review_status": "review_required"
    },
    {
      "jurisdiction_id": "singapore",
      "label": "Singapore",
      "region": "Asia-Pacific",
      "maturity_score": 55,
      "activity_score": 55,
      "freshness_score": 55,
      "confidence_score": 55,
      "maturity_level": "medium",
      "activity_level": "medium",
      "source_freshness": "medium",
      "coverage_confidence": "medium",
      "status_headline": "PDPC Model AI Governance + IMDA ecosystem",
      "latest_change_at": null,
      "source_count": 2,
      "regulation_count": 1,
      "review_required": true,
      "review_status": "review_required"
    },
    {
      "jurisdiction_id": "australia",
      "label": "Australia",
      "region": "Asia-Pacific",
      "maturity_score": 30,
      "activity_score": 30,
      "freshness_score": 30,
      "confidence_score": 30,
      "maturity_level": "low",
      "activity_level": "low",
      "source_freshness": "low",
      "coverage_confidence": "low",
      "status_headline": "AI ethics principles — voluntary federal guidance",
      "latest_change_at": null,
      "source_count": 0,
      "regulation_count": 1,
      "review_required": true,
      "review_status": "review_required"
    },
    {
      "jurisdiction_id": "japan",
      "label": "Japan",
      "region": "Asia-Pacific",
      "maturity_score": 55,
      "activity_score": 55,
      "freshness_score": 30,
      "confidence_score": 30,
      "maturity_level": "medium",
      "activity_level": "medium",
      "source_freshness": "low",
      "coverage_confidence": "low",
      "status_headline": "METI AI policy index (English)",
      "latest_change_at": null,
      "source_count": 0,
      "regulation_count": 1,
      "review_required": true,
      "review_status": "review_required"
    },
    {
      "jurisdiction_id": "south-korea",
      "label": "South Korea",
      "region": "Asia-Pacific",
      "maturity_score": 55,
      "activity_score": 55,
      "freshness_score": 55,
      "confidence_score": 55,
      "maturity_level": "medium",
      "activity_level": "medium",
      "source_freshness": "medium",
      "coverage_confidence": "medium",
      "status_headline": "PIPC AI and privacy hub",
      "latest_change_at": null,
      "source_count": 1,
      "regulation_count": 1,
      "review_required": true,
      "review_status": "review_required"
    },
    {
      "jurisdiction_id": "china",
      "label": "China",
      "region": "Asia-Pacific",
      "maturity_score": 55,
      "activity_score": 55,
      "freshness_score": 30,
      "confidence_score": 30,
      "maturity_level": "medium",
      "activity_level": "medium",
      "source_freshness": "low",
      "coverage_confidence": "low",
      "status_headline": "CAC generative AI measures (registry reference)",
      "latest_change_at": null,
      "source_count": 0,
      "regulation_count": 0,
      "review_required": true,
      "review_status": "review_required"
    },
    {
      "jurisdiction_id": "india",
      "label": "India",
      "region": "Asia-Pacific",
      "maturity_score": 30,
      "activity_score": 55,
      "freshness_score": 55,
      "confidence_score": 30,
      "maturity_level": "low",
      "activity_level": "medium",
      "source_freshness": "medium",
      "coverage_confidence": "low",
      "status_headline": "MeitY AI policy pages",
      "latest_change_at": null,
      "source_count": 1,
      "regulation_count": 1,
      "review_required": true,
      "review_status": "review_required"
    },
    {
      "jurisdiction_id": "brazil",
      "label": "Brazil",
      "region": "Americas",
      "maturity_score": 30,
      "activity_score": 55,
      "freshness_score": 55,
      "confidence_score": 30,
      "maturity_level": "low",
      "activity_level": "medium",
      "source_freshness": "medium",
      "coverage_confidence": "low",
      "status_headline": "PL 2338/2023 legislative tracking (Senado)",
      "latest_change_at": null,
      "source_count": 1,
      "regulation_count": 1,
      "review_required": true,
      "review_status": "review_required"
    },
    {
      "jurisdiction_id": "france",
      "label": "France",
      "region": "Europe",
      "maturity_score": 55,
      "activity_score": 55,
      "freshness_score": 55,
      "confidence_score": 30,
      "maturity_level": "medium",
      "activity_level": "medium",
      "source_freshness": "medium",
      "coverage_confidence": "low",
      "status_headline": "CNIL AI guidance hub",
      "latest_change_at": null,
      "source_count": 1,
      "regulation_count": 1,
      "review_required": true,
      "review_status": "review_required"
    },
    {
      "jurisdiction_id": "norway",
      "label": "Norway",
      "region": "Europe",
      "maturity_score": 55,
      "activity_score": 30,
      "freshness_score": 30,
      "confidence_score": 30,
      "maturity_level": "medium",
      "activity_level": "low",
      "source_freshness": "low",
      "coverage_confidence": "low",
      "status_headline": "EEA AI Act implementation planning",
      "latest_change_at": null,
      "source_count": 0,
      "regulation_count": 0,
      "review_required": true,
      "review_status": "review_required"
    },
    {
      "jurisdiction_id": "oecd",
      "label": "OECD",
      "region": "International",
      "maturity_score": 55,
      "activity_score": 55,
      "freshness_score": 55,
      "confidence_score": 55,
      "maturity_level": "medium",
      "activity_level": "medium",
      "source_freshness": "medium",
      "coverage_confidence": "medium",
      "status_headline": "OECD.AI Policy Observatory",
      "latest_change_at": null,
      "source_count": 1,
      "regulation_count": 1,
      "review_required": true,
      "review_status": "review_required"
    },
    {
      "jurisdiction_id": "coe",
      "label": "Council of Europe",
      "region": "Europe",
      "maturity_score": 55,
      "activity_score": 30,
      "freshness_score": 55,
      "confidence_score": 55,
      "maturity_level": "medium",
      "activity_level": "low",
      "source_freshness": "medium",
      "coverage_confidence": "medium",
      "status_headline": "AI Convention framework hub",
      "latest_change_at": null,
      "source_count": 1,
      "regulation_count": 1,
      "review_required": true,
      "review_status": "review_required"
    },
    {
      "jurisdiction_id": "unesco",
      "label": "UNESCO",
      "region": "International",
      "maturity_score": 30,
      "activity_score": 30,
      "freshness_score": 55,
      "confidence_score": 55,
      "maturity_level": "low",
      "activity_level": "low",
      "source_freshness": "medium",
      "coverage_confidence": "medium",
      "status_headline": "AI ethics recommendation hub",
      "latest_change_at": null,
      "source_count": 1,
      "regulation_count": 1,
      "review_required": true,
      "review_status": "review_required"
    },
    {
      "jurisdiction_id": "g7",
      "label": "G7",
      "region": "International",
      "maturity_score": 30,
      "activity_score": 30,
      "freshness_score": 30,
      "confidence_score": 30,
      "maturity_level": "low",
      "activity_level": "low",
      "source_freshness": "low",
      "coverage_confidence": "low",
      "status_headline": "Hiroshima AI Process (reference)",
      "latest_change_at": null,
      "source_count": 0,
      "regulation_count": 0,
      "review_required": true,
      "review_status": "review_required"
    }
  ],
  "legend": {
    "enacted": "Enacted / in force (curated metadata)",
    "proposed": "Proposed / draft",
    "guidance": "Guidance / framework",
    "monitoring": "Monitoring registered",
    "unknown": "Limited coverage"
  }
}
